socket_wait.py
socket_wait-0.1.2.dist-info/METADATA
socket_wait-0.1.2.dist-info/WHEEL
socket_wait-0.1.2.dist-info/entry_points.txt
socket_wait-0.1.2.dist-info/top_level.txt
socket_wait-0.1.2.dist-info/RECORD
