Metadata-Version: 2.1
Name: socket-wait
Version: 0.1.2
Summary: Listen on a port until a connection is received.
Home-page: https://github.com/tomplex/socket_wait
Author: Tom Caruso
Author-email: carusot42@gmail.com
License: UNKNOWN
Platform: UNKNOWN
Classifier: Programming Language :: Python
Classifier: Programming Language :: Python :: 3
Classifier: Programming Language :: Python :: Implementation :: CPython
